spaed/__init__.py
spaed/get_domain_seqs.py
spaed/pymol_vis.py
spaed/spaed.py
spaed-1.0.5.dist-info/METADATA
spaed-1.0.5.dist-info/WHEEL
spaed-1.0.5.dist-info/entry_points.txt
spaed-1.0.5.dist-info/licenses/LICENSE
spaed-1.0.5.dist-info/RECORD
