Metadata-Version: 2.4
Name: spaed
Version: 1.0.5
Summary: A module for the segmentation of phage endolysin domains based on the PAE matrix from AlphaFold.
Project-URL: Homepage, https://github.com/Rousseau-Team/spaed.git
Author-email: Alexandre Boulay <alexandre.boulay.6@ulaval.ca>
License-File: LICENSE
Keywords: bacteriophage,bioinformatics,delineation,domain,phage,protein,segmentation
Classifier: License :: OSI Approved :: GNU General Public License v3 (GPLv3)
Classifier: Programming Language :: Python :: 3
Requires-Python: >3.10
Requires-Dist: numpy
Requires-Dist: pandas
Requires-Dist: scipy
